{
  "network": {
    "variables": {
      "X": 3,
      "Y": 3,
      "Z": 3
    },
    "regulations": [
      {
        "target": "Y",
        "regulators": [{ "variable": "X", "thresholds": [1, 2] }],
        "contexts": [
          { "intervals": ["0"], "target_value": 0 },
          { "intervals": ["1"], "target_value": 1 },
          { "intervals": ["2"], "target_value": 2 }
        ]
      },
      {
        "target": "Z",
        "regulators": [
          { "variable": "X", "thresholds": [1, 2] },
          { "variable": "Y", "thresholds": [1, 2] }
        ],
        "contexts": [
          { "intervals": ["0", "0"], "target_value": 0 },
          { "intervals": ["1", "*"], "target_value": 1 },
          { "intervals": ["*", "1"], "target_value": 1 },
          { "intervals": ["2", "*"], "target_value": 2 },
          { "intervals": ["*", "2"], "target_value": 2 }
        ]
      }
    ]
  },
  "formula": "",
  "init_states": {}
}
